{
  "generator-magnetjs": {
    "promptValues": {
      "npmModule": "sequelize-fixtures",
      "moduleName": "magnet-sequelize-fixtures",
      "name": "Kieve Chua",
      "email": "kievechua@gmail.com",
      "website": "https://github.com/kievechua",
      "license": "MIT",
      "language": "ts",
      "includeFly": true,
      "fromDist": true
    },
    "npmModule": "sequelize-fixtures",
    "moduleName": "magnet-sequelize-fixtures",
    "name": "Kieve Chua",
    "email": "kievechua@gmail.com",
    "website": "https://github.com/kievechua",
    "license": "MIT",
    "language": "ts",
    "includeFly": true,
    "fromDist": true
  }
}